make_xuml_repo/__init__.py
make_xuml_repo/__main__.py
make_xuml_repo/exceptions.py
make_xuml_repo/log.conf
make_xuml_repo/metamodel.py
make_xuml_repo/metamodel/action.xcm
make_xuml_repo/metamodel/activity.xcm
make_xuml_repo/metamodel/attribute-access.xcm
make_xuml_repo/metamodel/class-attribute.xcm
make_xuml_repo/metamodel/computation.xcm
make_xuml_repo/metamodel/conditional-logic.xcm
make_xuml_repo/metamodel/create-delete.xcm
make_xuml_repo/metamodel/domain.xcm
make_xuml_repo/metamodel/event.xcm
make_xuml_repo/metamodel/external.xcm
make_xuml_repo/metamodel/flow.xcm
make_xuml_repo/metamodel/form.xcm
make_xuml_repo/metamodel/method-call.xcm
make_xuml_repo/metamodel/mm_types.yaml
make_xuml_repo/metamodel/nav.xcm
make_xuml_repo/metamodel/ref-action.xcm
make_xuml_repo/metamodel/rel.xcm
make_xuml_repo/metamodel/relational-action.xcm
make_xuml_repo/metamodel/scalar-action.xcm
make_xuml_repo/metamodel/select-action.xcm
make_xuml_repo/metamodel/signal-action.xcm
make_xuml_repo/metamodel/state.xcm
make_xuml_repo/metamodel/type.xcm
make_xuml_repo-0.14.0.dist-info/licenses/LICENSE
make_xuml_repo-0.14.0.dist-info/METADATA
make_xuml_repo-0.14.0.dist-info/WHEEL
make_xuml_repo-0.14.0.dist-info/entry_points.txt
make_xuml_repo-0.14.0.dist-info/top_level.txt
make_xuml_repo-0.14.0.dist-info/RECORD
