Metadata-Version: 2.4
Name: make-xuml-repo
Version: 0.14.0
Summary: Generates a database from a set of *.xcm (executable class model) files
Author-email: Leon Starr <leon_starr@modelint.com>
License: MIT License
Project-URL: repository, https://github.com/modelint/make-xuml-repo
Project-URL: documentation, https://github.com/modelint/make-xuml-repo/wiki
Keywords: action language,executable uml,mbse,xuml,xtuml,platform independent,sysml
Classifier: License :: OSI Approved :: MIT License
Classifier: Programming Language :: Python
Classifier: Programming Language :: Python :: 3
Requires-Python: >=3.11
License-File: LICENSE
Requires-Dist: PyYAML
Requires-Dist: xcm-parser
Requires-Dist: mi-pyral
Requires-Dist: tomli; python_version < "3.11"
Provides-Extra: build
Requires-Dist: build; extra == "build"
Requires-Dist: twine; extra == "build"
Provides-Extra: dev
Requires-Dist: bump2version; extra == "dev"
Requires-Dist: pytest; extra == "dev"
Dynamic: license-file
